{
  "kind": "collectionType",
  "collectionName": "product_tags",
  "info": {
    "singularName": "product-tag",
    "pluralName": "product-tags",
    "displayName": "Product Tag",
    "description": ""
  },
  "options": {
    "draftAndPublish": false
  },
  "pluginOptions": {},
  "attributes": {
    "tag": {
      "type": "string"
    },
    "product": {
      "type": "relation",
      "relation": "manyToOne",
      "target": "api::product.product",
      "inversedBy": "product_tags"
    }
  }
}
